ultra_sockets/UltraSockets.py
ultra_sockets/__init__.py
ultra_sockets-1.0.4.dist-info/LICENSE
ultra_sockets-1.0.4.dist-info/METADATA
ultra_sockets-1.0.4.dist-info/WHEEL
ultra_sockets-1.0.4.dist-info/top_level.txt
ultra_sockets-1.0.4.dist-info/RECORD
