Metadata-Version: 2.1
Name: ultra-sockets
Version: 1.0.4
Summary: Protocol to provide fast and light communication between devices over (W)LAN
Home-page: https://github.com/MugilanGN/UltraSockets
Author: Mugilan Ganesan
Author-email: mugi.ganesan@gmail.com
License: UNKNOWN
Platform: UNKNOWN
Classifier: Programming Language :: Python :: 3
Classifier: Operating System :: OS Independent
Classifier: License :: OSI Approved :: Apache Software License
Requires-Python: >=3.4
